{
  "annotations": {
    "changelogDate": "20251006122036"
  },
  "applications": ["myApp"],
  "dto": "mapstruct",
  "fields": [
    {
      "fieldName": "name",
      "fieldType": "String",
      "fieldValidateRules": ["maxlength"],
      "fieldValidateRulesMaxlength": "255"
    }
  ],
  "incrementalChangelog": false,
  "name": "Team",
  "pagination": "pagination",
  "relationships": [
    {
      "otherEntityName": "player",
      "otherEntityRelationshipName": "teams",
      "relationshipName": "players",
      "relationshipSide": "left",
      "relationshipType": "many-to-many"
    }
  ],
  "searchEngine": "no",
  "service": "serviceClass"
}
